AUTHORS
ChangeLog
LICENSE
README.md
requirements.txt
setup.cfg
setup.py
tox.ini
quince/__init__.py
quince/v1_impl.py
quince/v2_impl.py
quince.egg-info/PKG-INFO
quince.egg-info/SOURCES.txt
quince.egg-info/dependency_links.txt
quince.egg-info/not-zip-safe
quince.egg-info/pbr.json
quince.egg-info/requires.txt
quince.egg-info/top_level.txt