Metadata-Version: 1.1
Name: quince
Version: 0.3.dev10
Summary: Default implementation for Quincy
Home-page: https://github.com/stackforge/stacktach-quince
Author: Dark Secret Software Inc.
Author-email: admin@darksecretsoftware.com
License: Apache-2
Keywords: stacktach
Platform: UNKNOWN
Classifier: Development Status :: 5 - Production/Stable
Classifier: Environment :: Console
Classifier: Intended Audience :: Developers
Classifier: Intended Audience :: Information Technology
Classifier: License :: OSI Approved :: Apache Software License
Classifier: Operating System :: OS Independent
Classifier: Programming Language :: Python
Classifier: Topic :: Software Development :: Libraries :: Python Modules
